{"module": null, "class_name": "MyResNetModel", "config": {"name": "my_res_net_model", "trainable": true, "dtype": {"module": "keras", "class_name": "DTypePolicy", "config": {"name": "float32"}, "registered_name": null}}, "registered_name": "MyResNetModel", "build_config": {"input_shape": [null, 311, 1]}, "compile_config": {"optimizer": {"module": "keras.optimizers", "class_name": "Adam", "config": {"name": "adam", "learning_rate": 0.0010000000474974513, "weight_decay": null, "clipnorm": null, "global_clipnorm": null, "clipvalue": null, "use_ema": false, "ema_momentum": 0.99, "ema_overwrite_frequency": null, "loss_scale_factor": null, "gradient_accumulation_steps": null, "beta_1": 0.9, "beta_2": 0.999, "epsilon": 1e-07, "amsgrad": false}, "registered_name": null}, "loss": ["mse", null, null], "loss_weights": [1, 0, 0], "metrics": null, "weighted_metrics": null, "run_eagerly": false, "steps_per_execution": 1, "jit_compile": true}}